pip_upgrade/__init__.py
pip_upgrade/main.py
pip_upgrade_all-0.1.6.dist-info/LICENSE
pip_upgrade_all-0.1.6.dist-info/METADATA
pip_upgrade_all-0.1.6.dist-info/WHEEL
pip_upgrade_all-0.1.6.dist-info/entry_points.txt
pip_upgrade_all-0.1.6.dist-info/top_level.txt
pip_upgrade_all-0.1.6.dist-info/RECORD
