Metadata-Version: 2.2
Name: pip-upgrade-all
Version: 0.1.6
Summary: A tool to upgrade all outdated Python packages to their latest versions
Home-page: https://github.com/RenjiYuusei/pip-upgrade-all
Author: Yuusei
Author-email: daoluc.yy@gmail.com
Classifier: Programming Language :: Python :: 3
Classifier: License :: OSI Approved :: MIT License
Classifier: Operating System :: OS Independent
Requires-Python: >=3.10
License-File: LICENSE
Requires-Dist: packaging
Dynamic: author
Dynamic: author-email
Dynamic: classifier
Dynamic: description
Dynamic: description-content-type
Dynamic: home-page
Dynamic: requires-dist
Dynamic: requires-python
Dynamic: summary
